{
  "metadata": {
    "generated_at": "2026-04-06T15:21:34.315Z",
    "stage": "5-price",
    "tripadvisor_id": "g297435-d29530261"
  },
  "prices": {},
  "sample_attempts": {
    "2026-05-09": {
      "detail": "no_usable_rates",
      "fetched_at": "2026-04-06T00:39:31.575Z",
      "http_status": "",
      "source": "xotelo",
      "status": "no_data"
    },
    "2026-05-12": {
      "detail": "no_usable_rates",
      "fetched_at": "2026-04-06T00:48:41.836Z",
      "http_status": "",
      "source": "xotelo",
      "status": "no_data"
    },
    "2026-09-08": {
      "detail": "no_usable_rates",
      "fetched_at": "2026-04-06T00:53:53.890Z",
      "http_status": "",
      "source": "xotelo",
      "status": "no_data"
    },
    "2026-09-12": {
      "detail": "no_usable_rates",
      "fetched_at": "2026-04-06T00:55:11.604Z",
      "http_status": "",
      "source": "xotelo",
      "status": "no_data"
    }
  }
}
