{
  "iprefer": {
    "currency": "USD",
    "fetched_at": "2026-04-05T04:18:02.371Z",
    "months": {
      "2026-04": {
        "cash_available_nights": 27,
        "cash_max": "137.00",
        "cash_min": "132.00",
        "points_available_nights": 27,
        "points_max": "30000",
        "points_min": "30000"
      },
      "2026-05": {
        "cash_available_nights": 31,
        "cash_max": "166.00",
        "cash_min": "135.00",
        "points_available_nights": 31,
        "points_max": "30000",
        "points_min": "30000"
      },
      "2026-06": {
        "cash_available_nights": 30,
        "cash_max": "159.00",
        "cash_min": "135.00",
        "points_available_nights": 30,
        "points_max": "30000",
        "points_min": "30000"
      },
      "2026-07": {
        "cash_available_nights": 31,
        "cash_max": "151.00",
        "cash_min": "116.00",
        "points_available_nights": 31,
        "points_max": "30000",
        "points_min": "30000"
      },
      "2026-08": {
        "cash_available_nights": 31,
        "cash_max": "130.00",
        "cash_min": "116.00",
        "points_available_nights": 31,
        "points_max": "30000",
        "points_min": "30000"
      },
      "2026-09": {
        "cash_available_nights": 30,
        "cash_max": "184.00",
        "cash_min": "116.00",
        "points_available_nights": 24,
        "points_max": "30000",
        "points_min": "30000"
      },
      "2026-10": {
        "cash_available_nights": 31,
        "cash_max": "142.00",
        "cash_min": "116.00",
        "points_available_nights": 31,
        "points_max": "30000",
        "points_min": "30000"
      },
      "2026-11": {
        "cash_available_nights": 30,
        "cash_max": "154.00",
        "cash_min": "116.00",
        "points_available_nights": 30,
        "points_max": "30000",
        "points_min": "30000"
      },
      "2026-12": {
        "cash_available_nights": 31,
        "cash_max": "142.00",
        "cash_min": "116.00",
        "points_available_nights": 31,
        "points_max": "30000",
        "points_min": "30000"
      },
      "2027-01": {
        "cash_available_nights": 31,
        "cash_max": "179.00",
        "cash_min": "179.00",
        "points_available_nights": 31,
        "points_max": "30000",
        "points_min": "30000"
      },
      "2027-02": {
        "cash_available_nights": 28,
        "cash_max": "179.00",
        "cash_min": "179.00",
        "points_available_nights": 28,
        "points_max": "30000",
        "points_min": "30000"
      },
      "2027-03": {
        "cash_available_nights": 31,
        "cash_max": "179.00",
        "cash_min": "179.00",
        "points_available_nights": 31,
        "points_max": "30000",
        "points_min": "30000"
      },
      "2027-04": {
        "cash_available_nights": 30,
        "cash_max": "179.00",
        "cash_min": "179.00",
        "points_available_nights": 30,
        "points_max": "30000",
        "points_min": "30000"
      },
      "2027-05": {
        "cash_available_nights": 31,
        "cash_max": "179.00",
        "cash_min": "179.00",
        "points_available_nights": 31,
        "points_max": "30000",
        "points_min": "30000"
      },
      "2027-06": {
        "cash_available_nights": 30,
        "cash_max": "179.00",
        "cash_min": "179.00",
        "points_available_nights": 30,
        "points_max": "30000",
        "points_min": "30000"
      },
      "2027-07": {
        "cash_available_nights": 31,
        "cash_max": "179.00",
        "cash_min": "179.00",
        "points_available_nights": 31,
        "points_max": "30000",
        "points_min": "30000"
      },
      "2027-08": {
        "cash_available_nights": 31,
        "cash_max": "179.00",
        "cash_min": "179.00",
        "points_available_nights": 31,
        "points_max": "30000",
        "points_min": "30000"
      },
      "2027-09": {
        "cash_available_nights": 30,
        "cash_max": "179.00",
        "cash_min": "179.00",
        "points_available_nights": 30,
        "points_max": "30000",
        "points_min": "30000"
      },
      "2027-10": {
        "cash_available_nights": 3,
        "cash_max": "179.00",
        "cash_min": "179.00",
        "points_available_nights": 3,
        "points_max": "30000",
        "points_min": "30000"
      }
    }
  },
  "metadata": {
    "generated_at": "2026-04-15T16:23:48.658Z",
    "iprefer_source_id": "QROHS",
    "stage": "5-price"
  }
}
